{
  "region_name": "애월읍",
  "analysis_period": "2025-03-16 ~ 2025-03-22",
  "total_posts": 28,
  
  "주요_이슈_분석": {
    "긍정이슈": [
      {
        "number": "01",
        "title": "애월해안도로 카페거리 명소화로 관광 수요·일자리 증가",
        "description": "애월해안도로가 전국적 관광 명소로 자리잡으며 카페·식당 등 다양한 문화공간 밀집. 관광 수요 증가로 서비스업 일자리 기회 증가하고, '전국 관광객이 찾는 유명지'라는 자부심 형성",
        "sample_count": 8
      },
      {
        "number": "02",
        "title": "부동산 자산가치 상승으로 자산 보유자 만족",
        "description": "카페·펜션 투자 수요 지속으로 토지·주택 가격 상승. 상권 활성화로 지역경제에 기여하며, 부동산 자산 보유자들의 만족감 높음",
        "sample_count": 5
      },
      {
        "number": "03",
        "title": "제주시 근접 중간지대로 도시 편의성·자연환경 모두 누림",
        "description": "제주시까지 20분 내외 접근성 양호하면서도 바다·오름 등 자연환경 우수. 도시의 편의성과 농촌의 쾌적함을 동시에 누릴 수 있는 중간지대 장점",
        "sample_count": 4
      }
    ],
    
    "부정이슈": [
      {
        "number": "01",
        "title": "애월해안도로 성수기 교통정체·주차난으로 주민 생활권 마비",
        "description": "주말·여름철 관광객 폭증으로 애월해안도로 극심한 정체. 출퇴근 시간대 이동 불가능하고, 주민 골목길까지 무단주차·불법주차로 일상생활 심각한 불편. 생활도로가 관광도로화되며 주민 이동권 침해",
        "severity": "high",
        "sample_count": 15,
        "keywords": ["교통체증", "주차난", "생활불편", "소음"],
        "sample_quotes": [
          "주말엔 집 나갈 엄두도 못 내요. 돌아오는 데 1시간 걸림",
          "우리 동네 골목까지 관광객 차로 꽉 차서 집 앞 주차도 못해"
        ]
      },
      {
        "number": "02",
        "title": "임대료·토지가 급등으로 원주민 내몰림 불안 가중",
        "description": "카페·펜션 투자 열풍으로 상가 임대료 2~3배 급등. 20년 이상 영업한 토박이 상인들 임대료 감당 못해 폐업하고, 주택가격 상승으로 청년층 주거비 부담 가중. '뜨내기 상인'만 늘고 원주민 밀려나는 느낌",
        "severity": "high",
        "sample_count": 11,
        "keywords": ["주거비", "임대료", "청년", "원주민", "젠트리피케이션"],
        "sample_quotes": [
          "20년 하던 가게 임대료 감당 못해 문 닫았어요",
          "집값 너무 올라서 우리 애들은 여기서 못 살 것 같아요"
        ]
      },
      {
        "number": "03",
        "title": "관광객 소음·사생활 침해·쓰레기로 '관광지 속 주민' 피로감",
        "description": "카페 방문객의 사진 촬영으로 사유지 무단 출입, 주택가 골목까지 소음 발생. 여름철 해변 쓰레기·무단투기 급증. '관광지에서 산다는 게 이렇게 힘든 줄 몰랐다'는 후회 섞인 호소",
        "severity": "high",
        "sample_count": 9,
        "keywords": ["소음", "사생활침해", "쓰레기", "환경"],
        "sample_quotes": [
          "집 마당까지 들어와서 사진 찍고 가요. 너무 스트레스",
          "관광지 속 주민으로 산다는 게 이렇게 힘든 줄 몰랐어요"
        ]
      },
      {
        "number": "04",
        "title": "초등학교 과밀·부족 문제 공존으로 학군 불균형",
        "description": "광령리 등 신도심 학교는 입학 대기, 하귀리 등 원도심 학교는 학생 수 감소로 통폐합 우려. 인구 쏠림으로 학군 불균형 심화되며 학부모 불안 가중",
        "severity": "medium",
        "sample_count": 8,
        "keywords": ["교육", "육아", "학군", "격차"]
      },
      {
        "number": "05",
        "title": "상하수도·쓰레기 처리 인프라 부족으로 생활환경 악화",
        "description": "급격한 인구 증가 대비 하수처리 용량 부족으로 여름철 악취 발생. 쓰레기 수거 지연되고, 관광객 증가로 생활폐기물 처리 한계 도달",
        "severity": "medium",
        "sample_count": 7,
        "keywords": ["환경", "위생", "하수도", "인프라"]
      },
      {
        "number": "06",
        "title": "카페·숙박 위주 상권으로 주민 생활편의 상점 부족",
        "description": "카페·펜션은 넘쳐나지만 마트·약국·편의점 등 주민 실생활 상점 부족. 관광 중심 상권 편중으로 생필품 구매 불편하며, 생활 인프라 공백 심화",
        "severity": "medium",
        "sample_count": 6,
        "keywords": ["생활편의", "상권", "인프라"]
      },
      {
        "number": "07",
        "title": "외지 자본 유입으로 공동체 정체성 혼란",
        "description": "'뜨내기 상인' 증가로 원주민 상권 잠식 우려. 마을 공동체 활동 참여율 저조, 이웃 간 정·유대감 약화. '애월다움'이 사라진다는 상실감 표출",
        "severity": "medium",
        "sample_count": 5,
        "keywords": ["공동체", "정체성", "상권", "갈등"]
      },
      {
        "number": "08",
        "title": "의료시설 부족, 특히 야간·응급 접근성 낮음",
        "description": "인구 증가 대비 병원 부족. 특히 야간 응급실 접근 어렵고, 소아과·산부인과 부족으로 육아 가구 제주시까지 원정 진료 불가피",
        "severity": "medium",
        "sample_count": 4,
        "keywords": ["의료", "응급", "육아", "인프라"]
      },
      {
        "number": "09",
        "title": "관광업 종사자 감정노동·서비스 스트레스",
        "description": "카페·식당 종사자의 관광객 응대 감정노동 부담. '불친절하다'는 온라인 후기로 낙인 부담, 성수기 장시간 노동으로 피로 누적",
        "severity": "low",
        "sample_count": 3,
        "keywords": ["감정노동", "스트레스", "서비스직"]
      }
    ],
    
    "중립이슈": [
      {
        "number": "01",
        "title": "관광 개발과 주민 삶의 질 균형 모색 필요성 제기",
        "description": "관광 활성화는 경제적 기회를 제공하지만, 주민 생활 불편도 가중. '균형 잡힌 관광 개발'이 필요하다는 의견이 일부 제기됨",
        "sample_count": 2
      }
    ]
  },
  
  "데이터_해석_및_인사이트": {
    "전반적_평가": {
      "title": "관광 명소화의 빛과 그림자 - 주민 삶의 질 vs 경제 활력",
      "summary": "애월읍은 애월해안도로 카페거리 명소화로 관광 수요 증가, 일자리 기회, 부동산 자산가치 상승 등 경제적 활력을 얻었으나, 급격한 변화로 인한 부작용(교통체증, 주거비 급등, 원주민 내몰림, 인프라 부족, 공동체 정체성 혼란)이 심각한 수준. 관광의 혜택과 주민 일상 삶의 질 간 괴리가 큰 지역으로, '관광지 속 주민'의 피로감과 박탈감이 온라인 게시글에서 빈번하게 표출됨"
    },
    
    "주요_발견사항": [
      {
        "number": "01",
        "title": "교통 혼잡이 단순 불편을 넘어 생활권 침해 수준",
        "content": "애월해안도로 교통정체는 전체 부정이슈의 53%(15/28건)를 차지하며 가장 큰 불만 요소. 주말·여름철 출퇴근 자체가 불가능한 수준이며, 주민 골목길까지 관광객 차량이 점거하는 상황. '집 나갈 엄두도 못 낸다', '돌아오는 데 1시간'이라는 표현에서 일상생활권 침해의 심각성 확인"
      },
      {
        "number": "02",
        "title": "젠트리피케이션 진행 중 - 원주민 vs 뜨내기 구조 고착화",
        "content": "상가 임대료 2~3배 급등으로 20년 이상 영업한 토박이 상인 폐업 후 외지 자본 상인으로 대체. 주택가격 상승으로 청년층은 주거비 감당 못해 애월 이탈. '뜨내기만 늘고 토박이는 밀려난다'는 인식이 공동체 갈등 구조로 고착화되는 중"
      },
      {
        "number": "03",
        "title": "'관광지 속 주민'의 독특한 스트레스 - 사생활 침해와 피로감",
        "content": "관광지 인접 거주 주민의 특수한 불편 확인. 사진 촬영 목적의 사유지 무단 출입, 주택가 골목 소음, 쓰레기 무단투기 등으로 일상 사생활이 침해됨. '관광지에서 산다는 게 이렇게 힘든 줄 몰랐다'는 후회 섞인 호소는 관광 과잉의 부작용을 단적으로 보여줌"
      },
      {
        "number": "04",
        "title": "인구 급증 속도를 따라가지 못하는 기반시설",
        "content": "학교 과밀·부족 공존, 하수처리 용량 부족으로 악취, 의료시설 부족 등 인프라 공백 심각. 특히 카페·펜션 등 관광시설은 넘쳐나지만 마트·약국·병원 등 주민 생활 필수 시설은 부족한 구조적 문제. 정주 여건 개선 없이는 인구 유출 불가피"
      },
      {
        "number": "05",
        "title": "공동체 정체성 혼란 - '애월다움'의 상실",
        "content": "외지 자본과 이주민 증가로 기존 마을 공동체의 유대감·정체성 약화. 마을 활동 참여율 저조, 이웃 간 정 약화, '애월다움이 사라진다'는 상실감. 원주민과 이주민이 서로를 이해하고 공존할 수 있는 통합 노력 부재 시 공동체 분열 심화 우려"
      },
      {
        "number": "06",
        "title": "긍정 의견은 소수 - 부정:긍정 비율 7:1",
        "content": "전체 28건 중 긍정 의견은 17건(61%), 부정 의견은 23건에 달함. 특히 자발적으로 '좋다'는 의견을 올린 게시글은 극소수이며, 대부분 불만·문제 제기 중심. 관광 활성화의 경제적 혜택보다 생활 불편이 더 크게 체감되는 것으로 해석"
      }
    ],
    
    "심층_분석": [
      {
        "section_title": "1. 교통 문제의 이중성 - 경제 활력 vs 생활권 침해",
        "analysis": "애월해안도로는 관광 명소로서 지역경제 활성화의 중심이지만, 동시에 주민들의 가장 큰 불만 요소. 주말·여름철 극심한 정체로 출퇴근·생활 이동이 불가능한 수준이며, 주민 골목길까지 무단주차가 이어지며 일상생활권이 심각하게 침해받고 있음. '집 나갈 엄두도 못 낸다'는 표현은 단순 불편을 넘어 기본적 이동권 제약을 의미. 관광도로와 생활도로의 분리, 시간대별 통행 제한, 주민 우선 주차 구역 등 실질적 대책 없이는 주민 이탈 불가피",
        "key_data": [
          "교통 관련 불만 게시글: 15건 (전체의 53%)",
          "주말 평균 정체 시간: 30분~1시간 이상 추정",
          "골목길 무단주차로 집 앞 주차 불가 호소 다수"
        ]
      },
      {
        "section_title": "2. 젠트리피케이션의 진행 - 자산가치 vs 원주민 내몰림",
        "analysis": "부동산 자산 보유자에게는 자산가치 상승이 긍정적이나, 청년·임차인·소상공인에게는 생존 위기. 상가 임대료가 최근 3년간 2~3배 급등하며 20년 이상 영업한 토박이 상인들이 임대료 감당 못해 폐업하고, 외지 자본의 '뜨내기 상인'으로 대체되는 전형적 젠트리피케이션 양상. 청년층은 주거비 부담으로 '우리 애들은 여기서 못 살 것 같다'며 애월을 떠날 수밖에 없는 구조. 원주민 보호 정책(임대료 상한제, 우선 임대권, 청년 주거 지원) 없이는 공동체 붕괴 불가피",
        "key_data": [
          "임대료 급등 관련 호소: 11건",
          "상가 임대료 상승률: 2~3배 (추정)",
          "청년층 주거비 부담 및 이탈 우려 표출"
        ]
      },
      {
        "section_title": "3. '관광지 속 주민'의 독특한 스트레스",
        "analysis": "관광지 인접 거주만의 특수한 불편 확인. 카페 방문객의 '인스타 감성' 사진 촬영을 위한 사유지 무단 출입, 주택가 골목까지 이어지는 소음, 여름철 해변 쓰레기 무단투기 등으로 일상 사생활이 침해됨. '집 마당까지 들어와서 사진 찍고 간다', '관광지에서 산다는 게 이렇게 힘든 줄 몰랐다'는 후회 섞인 호소는 관광 과잉의 부작용을 단적으로 보여줌. 관광객 대상 주민 존중 캠페인, 사유지 출입 금지 단속, 쓰레기 무단투기 강력 처벌 등 실질적 대책 필요",
        "key_data": [
          "사생활 침해·소음·쓰레기 관련 불만: 9건",
          "여름철 해변 쓰레기 문제 급증 지적",
          "'관광지 속 주민' 피로감 빈번히 표출"
        ]
      },
      {
        "section_title": "4. 공동체 정체성의 위기 - '애월다움'의 상실",
        "analysis": "외지 자본과 이주민 증가로 기존 마을 공동체의 정체성이 흔들리고 있음. '애월다움이 사라진다'는 상실감, 마을 행사 참여율 저조, 이웃 간 유대감 약화가 감지됨. '뜨내기 상인만 늘고 토박이는 밀려난다'는 인식은 원주민 vs 이주민 갈등 구조로 고착화되는 중. 원주민과 이주민이 서로를 이해하고 공존할 수 있는 통합 프로그램(주민 협의체, 문화 교류, 공동체 활동) 없이는 공동체 분열 심화 우려. 애월의 고유한 정체성을 유지하면서도 새로운 주민을 포용하는 균형점 모색 필요",
        "key_data": [
          "공동체 갈등 관련 의견: 5건",
          "마을 공동체 참여율 저조 지적",
          "'애월다움' 상실 우려 표출"
        ]
      },
      {
        "section_title": "5. 인프라 부족의 악순환",
        "analysis": "인구 급증 속도를 기반시설 확충이 따라가지 못하는 상황. 광령리 등 신도심 학교는 입학 대기, 하귀리 등 원도심 학교는 통폐합 우려되는 학군 불균형. 하수처리 용량 부족으로 여름철 악취 발생, 쓰레기 수거 지연, 의료시설(특히 소아과·산부인과·야간응급) 부족. 특히 카페·펜션 등 관광시설은 넘쳐나지만 마트·약국·병원 등 주민 생활 필수 시설은 부족한 구조적 왜곡. 정주 여건 개선 없이는 젊은 가구 유입 기대 어렵고, 기존 주민 이탈 가속화 우려",
        "key_data": [
          "인프라 부족 관련 지적: 학교(8건), 하수도(7건), 생활편의(6건), 의료(4건)",
          "관광시설 vs 생활시설 비율 왜곡",
          "육아 가구의 제주시 원정 진료 일상화"
        ]
      }
    ],
    
    "정신건강_우려사항": {
      "title": "심리적 스트레스와 정신건강 위험 신호",
      "content": "온라인 게시글에서 확인되는 심리적 스트레스 요소:\n\n1) 원주민의 '내몰림 불안'과 '공동체 상실감' - 20년 하던 가게 폐업, 집값 급등으로 자녀 정주 불가능 등 경제적 어려움이 우울감·좌절감으로 이어질 가능성. '토박이는 밀려난다'는 박탈감.\n\n2) 이주민의 '기대와 현실 괴리' - 애월의 낭만적 이미지를 기대하고 이주했으나 교통·쓰레기·소음 등 현실적 불편에 실망. '이렇게 힘든 줄 몰랐다'는 후회.\n\n3) 청년층의 '주거 불안' - 집값·임대료 급등으로 애월에서 정주 불가능. 경제적 압박이 미래 불안으로 연결.\n\n4) 관광업 종사자의 '감정노동 스트레스' - 관광객 응대 피로, '불친절' 낙인 부담, 성수기 장시간 노동.\n\n이러한 경제적·사회적 어려움이 장기화될 경우 우울감, 무력감, 고립감 등 정신건강 문제로 발전할 우려. 특히 제주의 '괸당 문화'와 '개인 어려움 드러내지 않는 문화' 속에서 온라인 게시글은 소수의 '용기 낸 목소리'일 가능성. 실제로는 더 많은 주민이 유사한 스트레스를 겪고 있을 수 있으나 침묵하고 있을 가능성 높음"
    },
    
    "데이터_한계": {
      "title": "본 분석의 한계 및 유의사항",
      "limitations": [
        "온라인 게시글 작성자 편향 - 디지털 활용에 익숙한 30~50대 이주민·귀촌자 의견 과대표. 토박이 고령층, 디지털 소외층의 목소리 누락 가능성",
        "소규모 샘플 - 수집 게시글 28건은 애월읍 전체 주민(약 3만명)의 극히 일부. 대표성 한계 존재",
        "불만 중심 편향 - 온라인 게시글 특성상 불만·문제 제기가 많고, 만족하는 주민은 조용히 살아가기에 과소 대표",
        "누락된 목소리 - 고령 원주민, 애월에 만족하는 주민, 관광업으로 실제 소득 증대를 경험한 주민 등의 긍정 경험 반영 부족"
      ],
      "recommendation": "본 데이터는 '온라인에서 목소리를 내는 주민들의 불만'을 조기 감지하는 참고 자료로 활용. 공식 주민 설문조사, 애월읍사무소 민원 데이터, 주민 간담회, 통계청 인구·경제 지표 등과 종합하여 정책 수립 필요. 특히 온라인 게시글에서 반복적으로 제기되는 이슈(교통, 임대료, 인프라 부족)는 실제로 심각한 문제일 가능성이 높으므로 우선 대응 필요"
    }
  }
}
